maestro/__init__.py
maestro/notebook.py
maestro/widgets.py
maestro/classroom_db/__init__.py
maestro/classroom_db/classroom.py
maestro/classroom_db/nb_config.py
maestro/classroom_db/nb_config_example.py
maestro/classroom_db/nb_gradebook.py
maestro/classroom_db/queryable.py
maestro/cli/__init__.py
maestro/cli/commands.py
maestro/cli/config.py
maestro/cli/fuzzy_match.py
maestro/cli/nb.py
maestro/cli/utils.py
maestro/course/__init__.py
maestro/course/compilers/__init__.py
maestro/course/compilers/regex.py
maestro/course/compilers/regex_crosswords.py
maestro/grader/function_grader.py
maestro/regex/__init__.py
maestro/regex/json.py
maestro/regex/random_strings.py
maestro/regex/regex_tester.py
maestro/test/__init__.py
maestro/test/check_locals.py
maestro/test/checkio.py
maestro/test/checksecret.py
maestro/test/testfunc.py
maestro/types/__init__.py
maestro/types/base.py
maestro/types/examples.py
maestro/types/numbers.py
maestro/utils/__init__.py
maestro/utils/bultins.py
maestro/utils/exec.py
maestro/utils/text.py
maestro_tools-0.1.0.dist-info/entry_points.txt
maestro_tools-0.1.0.dist-info/LICENSE
maestro_tools-0.1.0.dist-info/WHEEL
maestro_tools-0.1.0.dist-info/METADATA
maestro_tools-0.1.0.dist-info/RECORD
