Metadata-Version: 2.1
Name: maestro-tools
Version: 0.1.0
Summary: Maestro is a collection of tools to aid teachers in programming-based 
Home-page: http://github.com/fabiommendes/maestro/
License: UNKNOWN
Author: Fábio Macêdo Mendes
Author-email: fabiomacedomendes@gmail.com
Classifier: License :: OSI Approved :: MIT License
Requires-Dist: pytest >= 4.0
Requires-Dist: click >= 7.0
Requires-Dist: hyperpython ~= 1.1.1
Requires-Dist: sidekick ~= 0.5.2
Requires-Dist: unidecode
Requires-Dist: toml
